<?xml version="1.0" encoding="UTF-8" standalone="yes"?>

<item>
<title>Mi Villano Favorito</title>        
<ol>https://openload.co/embed/G2io6TYAhlk/</ol>
<id_tmdb>20352</id_tmdb>
</item>

<item>
<title>Mi Villano Favorito 2</title>        
<ol>https://openload.co/embed/ZEzK1KegSh8/</ol>
<id_tmdb>93456</id_tmdb>
</item>

<item>
<title>Mi Villano Favorito 3</title>        
<ol>https://openload.co/embed/ogNooXlyd64/</ol>
<id_tmdb>324852</id_tmdb>
</item>

<item>
<title>Ferdinand</title>        
<ol>https://openload.co/embed/dnXtE1dA5eY/</ol>
<id_tmdb>364689</id_tmdb>
</item>

<item>
<title>Condorito</title>        
<ol>https://openload.co/embed/l9z6gO41R6w/</ol>
<id_tmdb>450314</id_tmdb>
</item>

<item>
<title>Emoji</title>        
<link>https://my.mail.ru/bk/pelicula.pelicula/video/_myvideo/5789.html</link>
<id_tmdb>378236</id_tmdb>
</item>

<item>
<title>Brujerias</title>        
<link>https://my.mail.ru/mail/aquipelis/video/_myvideo/5878.html</link>
<id_tmdb>417496</id_tmdb>
</item>

<item>
<title>Lego Friends: Girlz 4 Life </title>        
<link>https://my.mail.ru/mail/aquipelis/video/_myvideo/5936.html</link>
<id_tmdb>378858</id_tmdb>
</item>

<item>
<title>Las aventuras de Scooby Doo: El mapa misterioso</title>        
<link>https://my.mail.ru/mail/aquipelis/video/_myvideo/5741.html</link>
<id_tmdb>210769</id_tmdb>
</item>

<item>
<title>Boss Baby</title>        
<link>https://my.mail.ru/bk/pelicula.pelicula/video/_myvideo/5802.html</link>
<id_tmdb>295693</id_tmdb>
</item>

<item>
<title>Ozzy, rapido y peludo</title>        
<link>https://my.mail.ru/bk/pelicula.pelicula/video/_myvideo/5702.html</link>
<id_tmdb>411221</id_tmdb>
</item>

<item>
<title>Los Pitufos</title>        
<link>https://my.mail.ru/mail/aquipelis/video/_myvideo/5328.html</link>
<id_tmdb>41513</id_tmdb>
</item>

<item>
<title>Cars</title>        
<link>https://my.mail.ru/bk/pelicula.pelicula/video/_myvideo/5683.html</link>
<id_tmdb>920</id_tmdb>
</item>

<item>
<title>Sahara</title>        
<link>https://my.mail.ru/bk/pelicula.pelicula/video/_myvideo/5574.html</link>
<id_tmdb>423453</id_tmdb>
</item>

<item>
<title>Hotel Transylvania</title>        
<link>https://my.mail.ru/mail/katiaalejandra/video/_myvideo/90.html</link>
<id_tmdb>76492</id_tmdb>
</item>

<item>
<title>Hotel Transylvania 2</title>        
<link>https://my.mail.ru/bk/pelicula.pelicula/video/_myvideo/4731.html</link>
<id_tmdb>159824</id_tmdb>
</item>

<item>
<title>Hotel transilvania 3</title>        
<ol>https://openload.co/embed/a_jKpDdUt9o/</ol>
<id_tmdb>400155</id_tmdb>
</item>

<item>
<title>Blinky Bill</title>        
<link>https://my.mail.ru/bk/pelicula.pelicula/video/_myvideo/5412.html</link>
<id_tmdb>339669</id_tmdb>
</item>

<item>
<title>Cigueñas</title>        
<link>https://my.mail.ru/bk/pelicula.pelicula/video/_myvideo/5346.html</link>
<id_tmdb>332210</id_tmdb>
</item>

<item>
<title>Canta</title>        
<link>https://my.mail.ru/mail/katiaalejandra/video/_myvideo/88.html</link>
<id_tmdb>335797</id_tmdb>
</item>
